django_select2_autofill/__init__.py
django_select2_autofill/apps.py
django_select2_autofill/widgets.py
django_select2_autofill/static/django_select2_autofill/js/autofill.js
django_select2_autofill-0.1.4.dist-info/LICENSE
django_select2_autofill-0.1.4.dist-info/METADATA
django_select2_autofill-0.1.4.dist-info/WHEEL
django_select2_autofill-0.1.4.dist-info/top_level.txt
django_select2_autofill-0.1.4.dist-info/RECORD
